LICENSE
MANIFEST.in
README.rst
setup.cfg
setup.py
pageobject/__init__.py
pageobject/locator.py
pageobject/page.py
pageobject/pageobject.py
pageobject/pageobjectbase.py
pageobject/pageobjectlist.py
pageobject/pageobjectlistbase.py
pageobject/select.py
pageobject/singlepageobjectbase.py
pageobject/webdriver_monkey_patches.py
pageobject.egg-info/PKG-INFO
pageobject.egg-info/SOURCES.txt
pageobject.egg-info/dependency_links.txt
pageobject.egg-info/requires.txt
pageobject.egg-info/top_level.txt
pageobject/commands/__init__.py
pageobject/commands/clear.py
pageobject/commands/click.py
pageobject/commands/get_attribute.py
pageobject/commands/get_value.py
pageobject/commands/index.py
pageobject/commands/is_enabled.py
pageobject/commands/is_existing.py
pageobject/commands/is_interactive.py
pageobject/commands/is_visible.py
pageobject/commands/load.py
pageobject/commands/move_to.py
pageobject/commands/send_keys.py
pageobject/commands/set_value.py
pageobject/commands/text.py
pageobject/commands/text_values.py
pageobject/commands/wait_for_enabled.py
pageobject/commands/wait_for_exist.py
pageobject/commands/wait_for_interactive.py
pageobject/commands/wait_for_vanish.py
pageobject/commands/wait_for_visible.py
pageobject/commands/wait_until.py
pageobject/commands/webelement.py